fakeme/__init__.py
fakeme/cli/__init__.py
fakeme/cli/cli.py
fakeme/config.py
fakeme/core.py
fakeme/data/countries.json
fakeme/fields.py
fakeme/generator.py
fakeme/logic/relationships.py
fakeme/output.py
fakeme/rules.py
fakeme/schema.py
fakeme/tables.py
fakeme/utils.py
fakeme/values.py
fakeme/walker.py
fakeme-0.2.2.dist-info/entry_points.txt
fakeme-0.2.2.dist-info/LICENSE
fakeme-0.2.2.dist-info/WHEEL
fakeme-0.2.2.dist-info/METADATA
fakeme-0.2.2.dist-info/RECORD
