Metadata-Version: 2.1
Name: fakeme
Version: 0.2.2
Summary: Relative Data Generator: generate relative tables data, data generator for multi tables that depend on each other
Home-page: https://github.com/xnuinside/fakeme
License: MIT
Author: Iuliia Volkova
Author-email: xnuinside@gmail.com
Requires-Python: >=3.6.2,<4.0
Classifier: License :: OSI Approved :: MIT License
Classifier: Programming Language :: Python :: 3
Classifier: Programming Language :: Python :: 3.7
Classifier: Programming Language :: Python :: 3.8
Classifier: Programming Language :: Python :: 3.9
Classifier: Topic :: Software Development
Classifier: Topic :: Software Development :: Libraries
Classifier: Topic :: Software Development :: Libraries :: Python Modules
Classifier: Topic :: Utilities
Requires-Dist: mimesis (>=4.0,<5.0)
Requires-Dist: pandas (==1.1.5)
Requires-Dist: ply (>=3.11,<4.0)
Requires-Dist: pydantic (>=1.8.2,<2.0.0)
Requires-Dist: simple-ddl-parser (>=0.19.1,<0.20.0)
Project-URL: Repository, https://github.com/xnuinside/fakeme
